equidna/__init__.py
equidna/dataframe.py
equidna/selectors.py
equidna-0.1.0.dist-info/METADATA
equidna-0.1.0.dist-info/WHEEL
equidna-0.1.0.dist-info/licenses/LICENSE
equidna-0.1.0.dist-info/RECORD
