Metadata-Version: 2.3
Name: equidna
Version: 0.1.0
Summary: Extensible Query Interface for Data Analysis
Author-email: Daniel Mesejo <mesejoleon@gmail.com>
License: MIT License
Requires-Python: >=3.10
Requires-Dist: duckdb>=1.1.3
Requires-Dist: ibis-framework[duckdb]>=9.5.0
Requires-Dist: pyarrow>=17.0.0
